{
  "version": "6",
  "dialect": "sqlite",
  "id": "4c863bc0-631a-470d-8650-ee94db206d86",
  "prevId": "00000000-0000-0000-0000-000000000000",
  "tables": {
    "boards": {
      "name": "boards",
      "columns": {
        "id": {
          "name": "id",
          "type": "text",
          "primaryKey": true,
          "notNull": true,
          "autoincrement": false
        },
        "name": {
          "name": "name",
          "type": "text",
          "primaryKey": false,
          "notNull": true,
          "autoincrement": false
        },
        "description": {
          "name": "description",
          "type": "text",
          "primaryKey": false,
          "notNull": false,
          "autoincrement": false
        },
        "created_at_timestamp_ms": {
          "name": "created_at_timestamp_ms",
          "type": "integer",
          "primaryKey": false,
          "notNull": false,
          "autoincrement": false,
          "default": "(strftime('%s','now') * 1000)"
        },
        "project_id": {
          "name": "project_id",
          "type": "text",
          "primaryKey": false,
          "notNull": true,
          "autoincrement": false
        },
        "temp_db_id": {
          "name": "temp_db_id",
          "type": "text",
          "primaryKey": false,
          "notNull": true,
          "autoincrement": false
        }
      },
      "indexes": {
        "boards_tenant_id_idx": {
          "name": "boards_tenant_id_idx",
          "columns": [
            "temp_db_id"
          ],
          "isUnique": false
        }
      },
      "foreignKeys": {
        "boards_project_id_projects_id_fk": {
          "name": "boards_project_id_projects_id_fk",
          "tableFrom": "boards",
          "tableTo": "projects",
          "columnsFrom": [
            "project_id"
          ],
          "columnsTo": [
            "id"
          ],
          "onDelete": "cascade",
          "onUpdate": "no action"
        },
        "boards_temp_db_id_temp_dbs_id_fk": {
          "name": "boards_temp_db_id_temp_dbs_id_fk",
          "tableFrom": "boards",
          "tableTo": "temp_dbs",
          "columnsFrom": [
            "temp_db_id"
          ],
          "columnsTo": [
            "id"
          ],
          "onDelete": "cascade",
          "onUpdate": "no action"
        }
      },
      "compositePrimaryKeys": {},
      "uniqueConstraints": {},
      "checkConstraints": {}
    },
    "projects": {
      "name": "projects",
      "columns": {
        "id": {
          "name": "id",
          "type": "text",
          "primaryKey": true,
          "notNull": true,
          "autoincrement": false
        },
        "name": {
          "name": "name",
          "type": "text",
          "primaryKey": false,
          "notNull": true,
          "autoincrement": false
        },
        "description": {
          "name": "description",
          "type": "text",
          "primaryKey": false,
          "notNull": true,
          "autoincrement": false
        },
        "created_at_timestamp_ms": {
          "name": "created_at_timestamp_ms",
          "type": "integer",
          "primaryKey": false,
          "notNull": false,
          "autoincrement": false,
          "default": "(strftime('%s','now') * 1000)"
        },
        "temp_db_id": {
          "name": "temp_db_id",
          "type": "text",
          "primaryKey": false,
          "notNull": true,
          "autoincrement": false
        },
        "item_positions_in_the_project": {
          "name": "item_positions_in_the_project",
          "type": "text",
          "primaryKey": false,
          "notNull": true,
          "autoincrement": false,
          "default": "'{}'"
        }
      },
      "indexes": {
        "projects_tenant_id_idx": {
          "name": "projects_tenant_id_idx",
          "columns": [
            "temp_db_id"
          ],
          "isUnique": false
        }
      },
      "foreignKeys": {
        "projects_temp_db_id_temp_dbs_id_fk": {
          "name": "projects_temp_db_id_temp_dbs_id_fk",
          "tableFrom": "projects",
          "tableTo": "temp_dbs",
          "columnsFrom": [
            "temp_db_id"
          ],
          "columnsTo": [
            "id"
          ],
          "onDelete": "cascade",
          "onUpdate": "no action"
        }
      },
      "compositePrimaryKeys": {},
      "uniqueConstraints": {},
      "checkConstraints": {}
    },
    "temp_dbs": {
      "name": "temp_dbs",
      "columns": {
        "id": {
          "name": "id",
          "type": "text",
          "primaryKey": true,
          "notNull": true,
          "autoincrement": false
        },
        "created_at_timestamp_ms": {
          "name": "created_at_timestamp_ms",
          "type": "integer",
          "primaryKey": false,
          "notNull": false,
          "autoincrement": false,
          "default": "(strftime('%s','now') * 1000)"
        },
        "expiry_timestamp_ms": {
          "name": "expiry_timestamp_ms",
          "type": "integer",
          "primaryKey": false,
          "notNull": true,
          "autoincrement": false
        }
      },
      "indexes": {},
      "foreignKeys": {},
      "compositePrimaryKeys": {},
      "uniqueConstraints": {},
      "checkConstraints": {}
    },
    "todo_items": {
      "name": "todo_items",
      "columns": {
        "id": {
          "name": "id",
          "type": "text",
          "primaryKey": true,
          "notNull": true,
          "autoincrement": false
        },
        "title": {
          "name": "title",
          "type": "text",
          "primaryKey": false,
          "notNull": true,
          "autoincrement": false
        },
        "description": {
          "name": "description",
          "type": "text",
          "primaryKey": false,
          "notNull": false,
          "autoincrement": false
        },
        "created_at_timestamp_ms": {
          "name": "created_at_timestamp_ms",
          "type": "integer",
          "primaryKey": false,
          "notNull": false,
          "autoincrement": false,
          "default": "(strftime('%s','now') * 1000)"
        },
        "boardId": {
          "name": "boardId",
          "type": "text",
          "primaryKey": false,
          "notNull": true,
          "autoincrement": false
        },
        "temp_db_id": {
          "name": "temp_db_id",
          "type": "text",
          "primaryKey": false,
          "notNull": true,
          "autoincrement": false
        }
      },
      "indexes": {
        "todo_items_tenant_id_idx": {
          "name": "todo_items_tenant_id_idx",
          "columns": [
            "temp_db_id"
          ],
          "isUnique": false
        }
      },
      "foreignKeys": {
        "todo_items_boardId_boards_id_fk": {
          "name": "todo_items_boardId_boards_id_fk",
          "tableFrom": "todo_items",
          "tableTo": "boards",
          "columnsFrom": [
            "boardId"
          ],
          "columnsTo": [
            "id"
          ],
          "onDelete": "cascade",
          "onUpdate": "no action"
        },
        "todo_items_temp_db_id_temp_dbs_id_fk": {
          "name": "todo_items_temp_db_id_temp_dbs_id_fk",
          "tableFrom": "todo_items",
          "tableTo": "temp_dbs",
          "columnsFrom": [
            "temp_db_id"
          ],
          "columnsTo": [
            "id"
          ],
          "onDelete": "cascade",
          "onUpdate": "no action"
        }
      },
      "compositePrimaryKeys": {},
      "uniqueConstraints": {},
      "checkConstraints": {}
    },
    "users": {
      "name": "users",
      "columns": {
        "id": {
          "name": "id",
          "type": "text",
          "primaryKey": true,
          "notNull": true,
          "autoincrement": false
        },
        "name": {
          "name": "name",
          "type": "text",
          "primaryKey": false,
          "notNull": true,
          "autoincrement": false
        },
        "age": {
          "name": "age",
          "type": "integer",
          "primaryKey": false,
          "notNull": true,
          "autoincrement": false
        },
        "email": {
          "name": "email",
          "type": "text",
          "primaryKey": false,
          "notNull": true,
          "autoincrement": false
        },
        "temp_db_id": {
          "name": "temp_db_id",
          "type": "text",
          "primaryKey": false,
          "notNull": true,
          "autoincrement": false
        }
      },
      "indexes": {
        "users_tenant_id_idx": {
          "name": "users_tenant_id_idx",
          "columns": [
            "temp_db_id"
          ],
          "isUnique": false
        },
        "users_email_unique_tempdbid": {
          "name": "users_email_unique_tempdbid",
          "columns": [
            "email",
            "temp_db_id"
          ],
          "isUnique": true
        }
      },
      "foreignKeys": {
        "users_temp_db_id_temp_dbs_id_fk": {
          "name": "users_temp_db_id_temp_dbs_id_fk",
          "tableFrom": "users",
          "tableTo": "temp_dbs",
          "columnsFrom": [
            "temp_db_id"
          ],
          "columnsTo": [
            "id"
          ],
          "onDelete": "cascade",
          "onUpdate": "no action"
        }
      },
      "compositePrimaryKeys": {},
      "uniqueConstraints": {},
      "checkConstraints": {}
    }
  },
  "views": {},
  "enums": {},
  "_meta": {
    "schemas": {},
    "tables": {},
    "columns": {}
  },
  "internal": {
    "indexes": {}
  }
}